[
    {
        "regiao": "NACIONAL",
        "titulo": "IME - Instituto Militar de Engenharia",
        "link": "https:\/\/www.pciconcursos.com.br\/noticias\/ime-abre-concurso-para-engenheiros-com-salario-inicial-de-8-2-mil",
        "imagem": "data:image\/png;base64,iVBORw0KGgoAAAANSUhEUgAAAAEAAAABCAYAAAAfFcSJAAAACXBIWXMAAA7EAAAOxAGVKw4bAAAADUlEQVQImWP4\/\/8\/AwAI\/AL+hc2rNAAAAABJRU5ErkJggg==",
        "resumo": "35 vagas até R$ 8245,00 Curso de Formação de Oficiais da Ativa Superior",
        "periodo_inscricao": "09\/07\/2025",
        "situacao": "Inscrição não iniciada",
        "link_apostila": [],
        "link_edital": [
            {
                "titulo": "EDITAL DE ABERTURA Nº 04\/2025",
                "url": "https:\/\/arq.pciconcursos.com.br\/ime-abre-concurso-para-engenheiros-com-salario-inicial-de-8-2-mil\/1675832\/0ab8730d4f\/edital_de_abertura_n_04_2025_1675832.pdf"
            }
        ],
        "detalhes_extraidos": {
            "cargos": [
                {
                    "cargo": "Engenheiro",
                    "vagas": null,
                    "salario": "R$ ,"
                }
            ]
        }
    },
    {
        "regiao": "NACIONAL",
        "titulo": "Polícia Federal",
        "link": "https:\/\/www.pciconcursos.com.br\/noticias\/policia-federal-informa-abertura-de-concurso-publico-com-1000-vagas",
        "imagem": "data:image\/png;base64,iVBORw0KGgoAAAANSUhEUgAAAAEAAAABCAYAAAAfFcSJAAAACXBIWXMAAA7EAAAOxAGVKw4bAAAADUlEQVQImWP4\/\/8\/AwAI\/AL+hc2rNAAAAABJRU5ErkJggg==",
        "resumo": "1000 vagas até R$ 26.800,00 Vários Cargos Superior",
        "periodo_inscricao": "13\/06\/2025",
        "situacao": "Inscrição não iniciada",
        "link_apostila": [],
        "link_edital": [
            {
                "titulo": "EDITAL DE ABERTURA Nº 01\/2025",
                "url": "https:\/\/arq.pciconcursos.com.br\/policia-federal-informa-abertura-de-concurso-publico-com-1000-vagas\/1675442\/b601edf0b0\/edital_de_abertura_n_01_2025_1675442.pdf"
            }
        ]
    },
    {
        "regiao": "SÃO PAULO",
        "titulo": "CRC - Conselho Regional de Contabilidade",
        "link": "https:\/\/www.pciconcursos.com.br\/noticias\/crc-sp-promove-concurso-publico-com-salarios-de-ate-11-6-mil",
        "imagem": "data:image\/png;base64,iVBORw0KGgoAAAANSUhEUgAAAAEAAAABCAYAAAAfFcSJAAAACXBIWXMAAA7EAAAOxAGVKw4bAAAADUlEQVQImWP4\/\/8\/AwAI\/AL+hc2rNAAAAABJRU5ErkJggg==",
        "resumo": "14 vagas até R$ 11.683,00 Vários Cargos Médio \/ Superior",
        "periodo_inscricao": "05\/06\/2025",
        "situacao": "Inscrição não iniciada",
        "link_apostila": [],
        "link_edital": [
            {
                "titulo": "EDITAL DE ABERTURA Nº 01\/2025",
                "url": "https:\/\/arq.pciconcursos.com.br\/crc-sp-promove-concurso-publico-com-salarios-de-ate-11-6-mil\/1672886\/5daebc7a97\/edital_de_abertura_n_01_2025_1672886.pdf"
            }
        ]
    },
    {
        "regiao": "SÃO PAULO",
        "titulo": "PM - Polícia Militar do Estado de São Paulo",
        "link": "https:\/\/www.pciconcursos.com.br\/noticias\/pm-sp-promove-concurso-publico-com-165-vagas-para-aluno-oficial",
        "imagem": "data:image\/png;base64,iVBORw0KGgoAAAANSUhEUgAAAAEAAAABCAYAAAAfFcSJAAAACXBIWXMAAA7EAAAOxAGVKw4bAAAADUlEQVQImWP4\/\/8\/AwAI\/AL+hc2rNAAAAABJRU5ErkJggg==",
        "resumo": "165 vagas até R$ 4833,27 Aluno-Oficial PMEnsino Médio",
        "periodo_inscricao": "02\/06\/2025",
        "situacao": "Inscrição não iniciada",
        "link_apostila": [],
        "link_edital": [
            {
                "titulo": "EDITAL DE ABERTURA Nº 1\/321\/25",
                "url": "https:\/\/arq.pciconcursos.com.br\/pm-sp-promove-concurso-publico-com-165-vagas-para-aluno-oficial\/1673497\/178d6d60bd\/edital_de_abertura_n_1_321_25_1673497.pdf"
            }
        ]
    },
    {
        "regiao": "SÃO PAULO",
        "titulo": "Prefeitura de Águas de Lindóia",
        "link": "https:\/\/www.pciconcursos.com.br\/noticias\/prefeitura-de-aguas-de-lindoia-sp-anuncia-concurso-publico-com-salarios-de-ate-5-4-mil",
        "imagem": "data:image\/png;base64,iVBORw0KGgoAAAANSUhEUgAAAAEAAAABCAYAAAAfFcSJAAAACXBIWXMAAA7EAAAOxAGVKw4bAAAADUlEQVQImWP4\/\/8\/AwAI\/AL+hc2rNAAAAABJRU5ErkJggg==",
        "resumo": "14 vagas até R$ 5495,00 Vários Cargos Médio \/ Superior",
        "periodo_inscricao": "09\/06\/2025",
        "situacao": "Inscrição não iniciada",
        "link_apostila": [],
        "link_edital": [
            {
                "titulo": "EDITAL DE ABERTURA Nº 01\/2025",
                "url": "https:\/\/arq.pciconcursos.com.br\/prefeitura-de-aguas-de-lindoia-sp-anuncia-concurso-publico-com-salarios-de-ate-5-4-mil\/1674234\/78c6a5bcf6\/edital_de_abertura_n_01_2025_1674234.pdf"
            }
        ]
    },
    {
        "regiao": "SÃO PAULO",
        "titulo": "Prefeitura de Caieiras",
        "link": "https:\/\/www.pciconcursos.com.br\/noticias\/prefeitura-de-caieiras-sp-promove-concurso-publico-para-assistentes-de-educacao-especializada",
        "imagem": "data:image\/png;base64,iVBORw0KGgoAAAANSUhEUgAAAAEAAAABCAYAAAAfFcSJAAAACXBIWXMAAA7EAAAOxAGVKw4bAAAADUlEQVQImWP4\/\/8\/AwAI\/AL+hc2rNAAAAABJRU5ErkJggg==",
        "resumo": "5 vagas até R$ 1833,21 Assistente de Educação Especializada Ensino Médio",
        "periodo_inscricao": "02\/06\/2025",
        "situacao": "Inscrição não iniciada",
        "link_apostila": [],
        "link_edital": [
            {
                "titulo": "EDITAL DE ABERTURA Nº 01\/2025",
                "url": "https:\/\/arq.pciconcursos.com.br\/prefeitura-de-caieiras-sp-promove-concurso-publico-para-assistentes-de-educacao-especializada\/1673989\/7137704743\/edital_de_abertura_n_01_2025_1673989.pdf"
            }
        ]
    },
    {
        "regiao": "SÃO PAULO",
        "titulo": "Prefeitura de Campinas",
        "link": "https:\/\/www.pciconcursos.com.br\/noticias\/prefeitura-de-campinas-sp-promove-concurso-publico-com-40-vagas",
        "imagem": "data:image\/png;base64,iVBORw0KGgoAAAANSUhEUgAAAAEAAAABCAYAAAAfFcSJAAAACXBIWXMAAA7EAAAOxAGVKw4bAAAADUlEQVQImWP4\/\/8\/AwAI\/AL+hc2rNAAAAABJRU5ErkJggg==",
        "resumo": "40 vagas até R$ 7481,28 Vários Cargos Fundamental \/ Superior",
        "periodo_inscricao": "23\/06\/2025",
        "situacao": "Inscrição não iniciada",
        "link_apostila": [],
        "link_edital": [
            {
                "titulo": "EDITAL DE ABERTURA Nº 03\/2025",
                "url": "https:\/\/arq.pciconcursos.com.br\/prefeitura-de-campinas-sp-promove-concurso-publico-com-40-vagas\/1673571\/3d95c06b09\/edital_de_abertura_n_03_2025_1673571.pdf"
            }
        ]
    },
    {
        "regiao": "SÃO PAULO",
        "titulo": "Prefeitura de Francisco Morato",
        "link": "https:\/\/www.pciconcursos.com.br\/noticias\/prefeitura-de-francisco-morato-sp-reabre-inscricoes-de-concurso-publico-para-guarda-civil-municipal",
        "imagem": "data:image\/png;base64,iVBORw0KGgoAAAANSUhEUgAAAAEAAAABCAYAAAAfFcSJAAAACXBIWXMAAA7EAAAOxAGVKw4bAAAADUlEQVQImWP4\/\/8\/AwAI\/AL+hc2rNAAAAABJRU5ErkJggg==",
        "resumo": "28 vagas até R$ 7159,78 Vários Cargos Fundamental \/ Médio \/ Técnico \/ Superior",
        "periodo_inscricao": "Conferir período por edital23\/06\/2025",
        "situacao": "Indefinido",
        "link_apostila": [],
        "link_edital": [
            {
                "titulo": "EDITAL DE ABERTURA Nº 01\/2025",
                "url": "https:\/\/arq.pciconcursos.com.br\/prefeitura-de-francisco-morato-sp-reabre-inscricoes-de-concurso-publico-para-guarda-civil-municipal\/1672508\/0aac4aad77\/edital_de_abertura_n_01_2025_1672508.pdf"
            },
            {
                "titulo": "EDITAL DE ABERTURA Nº 02\/2025 - RETIFICADO",
                "url": "https:\/\/arq.pciconcursos.com.br\/prefeitura-de-francisco-morato-sp-reabre-inscricoes-de-concurso-publico-para-guarda-civil-municipal\/1672509\/f61892b0dc\/edital_de_abertura_n_02_2025_retificado_1672509.pdf"
            },
            {
                "titulo": "RETIFICAÇÃO I - EDITAL Nº 02\/2025",
                "url": "https:\/\/arq.pciconcursos.com.br\/prefeitura-de-francisco-morato-sp-reabre-inscricoes-de-concurso-publico-para-guarda-civil-municipal\/1672832\/a761d9d35a\/retificacao_i_edital_n_02_2025_1672832.pdf"
            },
            {
                "titulo": "RETIFICAÇÃO II - EDITAL Nº 02\/2025",
                "url": "https:\/\/arq.pciconcursos.com.br\/prefeitura-de-francisco-morato-sp-reabre-inscricoes-de-concurso-publico-para-guarda-civil-municipal\/1674534\/f860ee28ff\/retificacao_ii_edital_n_02_2025_1674534.pdf"
            },
            {
                "titulo": "EDITAL DE ABERTURA Nº 03\/2025 - RETIFICADO",
                "url": "https:\/\/arq.pciconcursos.com.br\/prefeitura-de-francisco-morato-sp-reabre-inscricoes-de-concurso-publico-para-guarda-civil-municipal\/1672510\/968b759349\/edital_de_abertura_n_03_2025_retificado_1672510.pdf"
            },
            {
                "titulo": "REABERTURA - EDITAL Nº 03\/2025",
                "url": "https:\/\/arq.pciconcursos.com.br\/prefeitura-de-francisco-morato-sp-reabre-inscricoes-de-concurso-publico-para-guarda-civil-municipal\/1675438\/5138addf78\/reabertura_edital_n_03_2025_1675438.pdf"
            }
        ]
    },
    {
        "regiao": "SÃO PAULO",
        "titulo": "Prefeitura de Iperó",
        "link": "https:\/\/www.pciconcursos.com.br\/noticias\/prefeitura-de-ipero-sp-abre-vagas-em-diversos-setores-por-meio-de-concursos-publicos-e-processo-seletivo",
        "imagem": "data:image\/png;base64,iVBORw0KGgoAAAANSUhEUgAAAAEAAAABCAYAAAAfFcSJAAAACXBIWXMAAA7EAAAOxAGVKw4bAAAADUlEQVQImWP4\/\/8\/AwAI\/AL+hc2rNAAAAABJRU5ErkJggg==",
        "resumo": "65 vagas até R$ 5661,16 Vários Cargos Fundamental \/ Médio \/ Superior",
        "periodo_inscricao": "06\/06\/2025",
        "situacao": "Inscrição não iniciada",
        "link_apostila": [],
        "link_edital": [
            {
                "titulo": "EDITAL DE ABERTURA Nº 01\/2025 - PROCESSO SELETIVO",
                "url": "https:\/\/arq.pciconcursos.com.br\/prefeitura-de-ipero-sp-abre-vagas-em-diversos-setores-por-meio-de-concursos-publicos-e-processo-seletivo\/1674708\/ae1962536d\/edital_de_abertura_n_01_2025_processo_seletivo_1674708.pdf"
            },
            {
                "titulo": "EDITAL DE ABERTURA Nº 01\/2025 - CONCURSO PÚBLICO",
                "url": "https:\/\/arq.pciconcursos.com.br\/prefeitura-de-ipero-sp-abre-vagas-em-diversos-setores-por-meio-de-concursos-publicos-e-processo-seletivo\/1674709\/994d18f44b\/edital_de_abertura_n_01_2025_concurso_publico_1674709.pdf"
            },
            {
                "titulo": "EDITAL DE ABERTURA Nº 02\/2025 - CONCURSO PÚBLICO",
                "url": "https:\/\/arq.pciconcursos.com.br\/prefeitura-de-ipero-sp-abre-vagas-em-diversos-setores-por-meio-de-concursos-publicos-e-processo-seletivo\/1674710\/76bf3a3520\/edital_de_abertura_n_02_2025_concurso_publico_1674710.pdf"
            },
            {
                "titulo": "EDITAL DE ABERTURA Nº 03\/2025 - CONCURSO PÚBLICO",
                "url": "https:\/\/arq.pciconcursos.com.br\/prefeitura-de-ipero-sp-abre-vagas-em-diversos-setores-por-meio-de-concursos-publicos-e-processo-seletivo\/1674711\/8c4f79347b\/edital_de_abertura_n_03_2025_concurso_publico_1674711.pdf"
            },
            {
                "titulo": "EDITAL DE ABERTURA Nº 04\/2025 - CONCURSO PÚBLICO",
                "url": "https:\/\/arq.pciconcursos.com.br\/prefeitura-de-ipero-sp-abre-vagas-em-diversos-setores-por-meio-de-concursos-publicos-e-processo-seletivo\/1674712\/55d8092d83\/edital_de_abertura_n_04_2025_concurso_publico_1674712.pdf"
            },
            {
                "titulo": "EDITAL DE ABERTURA Nº 05\/2025 - CONCURSO PÚBLICO",
                "url": "https:\/\/arq.pciconcursos.com.br\/prefeitura-de-ipero-sp-abre-vagas-em-diversos-setores-por-meio-de-concursos-publicos-e-processo-seletivo\/1674713\/0d30b6ffd0\/edital_de_abertura_n_05_2025_concurso_publico_1674713.pdf"
            }
        ]
    },
    {
        "regiao": "SÃO PAULO",
        "titulo": "Prefeitura de São José dos Campos",
        "link": "https:\/\/www.pciconcursos.com.br\/noticias\/prefeitura-de-sao-jose-dos-campos-sp-retifica-edital-de-concurso-publico",
        "imagem": "data:image\/png;base64,iVBORw0KGgoAAAANSUhEUgAAAAEAAAABCAYAAAAfFcSJAAAACXBIWXMAAA7EAAAOxAGVKw4bAAAADUlEQVQImWP4\/\/8\/AwAI\/AL+hc2rNAAAAABJRU5ErkJggg==",
        "resumo": "16 vagas até R$ 4938,53 Vários Cargos Médio \/ Técnico \/ Superior",
        "periodo_inscricao": "12\/06\/2025",
        "situacao": "Inscrição não iniciada",
        "link_apostila": [],
        "link_edital": [
            {
                "titulo": "EDITAL DE ABERTURA Nº 01\/2025 - RETIFICADO",
                "url": "https:\/\/arq.pciconcursos.com.br\/prefeitura-de-sao-jose-dos-campos-sp-retifica-edital-de-concurso-publico\/1674115\/3662582e79\/edital_de_abertura_n_01_2025_retificado_1674115.pdf"
            },
            {
                "titulo": "RETIFICAÇÃO I",
                "url": "https:\/\/arq.pciconcursos.com.br\/prefeitura-de-sao-jose-dos-campos-sp-retifica-edital-de-concurso-publico\/1675485\/5b08f419e3\/retificacao_i_1675485.pdf"
            }
        ]
    },
    {
        "regiao": "SÃO PAULO",
        "titulo": "TJM - Tribunal de Justiça Militar",
        "link": "https:\/\/www.pciconcursos.com.br\/noticias\/edital-de-concurso-publico-e-divulgado-pelo-tjm-sp",
        "imagem": "data:image\/png;base64,iVBORw0KGgoAAAANSUhEUgAAAAEAAAABCAYAAAAfFcSJAAAACXBIWXMAAA7EAAAOxAGVKw4bAAAADUlEQVQImWP4\/\/8\/AwAI\/AL+hc2rNAAAAABJRU5ErkJggg==",
        "resumo": "4 vagas até R$ 8514,27 Vários Cargos Médio \/ Superior",
        "periodo_inscricao": "09\/06\/2025",
        "situacao": "Inscrição não iniciada",
        "link_apostila": [],
        "link_edital": [
            {
                "titulo": "EDITAL DE ABERTURA Nº 001\/2025",
                "url": "https:\/\/arq.pciconcursos.com.br\/edital-de-concurso-publico-e-divulgado-pelo-tjm-sp\/1673750\/46d4d33805\/edital_de_abertura_n_001_2025_1673750.pdf"
            }
        ]
    },
    {
        "regiao": "RIO DE JANEIRO",
        "titulo": "Prefeitura de Belford Roxo",
        "link": "https:\/\/www.pciconcursos.com.br\/noticias\/prefeitura-de-belford-roxo-rj-abre-concurso-publico-com-mais-de-1700-vagas",
        "imagem": "data:image\/png;base64,iVBORw0KGgoAAAANSUhEUgAAAAEAAAABCAYAAAAfFcSJAAAACXBIWXMAAA7EAAAOxAGVKw4bAAAADUlEQVQImWP4\/\/8\/AwAI\/AL+hc2rNAAAAABJRU5ErkJggg==",
        "resumo": "1723 vagas até R$ 2300,00 Vários Cargos Médio \/ Superior",
        "periodo_inscricao": "09\/06\/2025",
        "situacao": "Inscrição não iniciada",
        "link_apostila": [],
        "link_edital": [
            {
                "titulo": "EDITAL DE ABERTURA Nº 01\/2025",
                "url": "https:\/\/arq.pciconcursos.com.br\/prefeitura-de-belford-roxo-rj-abre-concurso-publico-com-mais-de-1700-vagas\/1673674\/3d28a9ffb4\/edital_de_abertura_n_01_2025_1673674.pdf"
            }
        ]
    },
    {
        "regiao": "RIO DE JANEIRO",
        "titulo": "Prefeitura de Duque de Caxias",
        "link": "https:\/\/www.pciconcursos.com.br\/noticias\/prefeitura-de-duque-de-caxias-rj-retifica-concurso-publico-com-400-vagas-para-guarda-civil-municipal",
        "imagem": "data:image\/png;base64,iVBORw0KGgoAAAANSUhEUgAAAAEAAAABCAYAAAAfFcSJAAAACXBIWXMAAA7EAAAOxAGVKw4bAAAADUlEQVQImWP4\/\/8\/AwAI\/AL+hc2rNAAAAABJRU5ErkJggg==",
        "resumo": "400 vagas até R$ 1456,25 Guarda Civil Municipal Ensino Médio",
        "periodo_inscricao": "Prorrogado até09\/06\/2025",
        "situacao": "Prorrogado",
        "link_apostila": [],
        "link_edital": [
            {
                "titulo": "EDITAL DE ABERTURA Nº 01\/2025 - RETIFICADO",
                "url": "https:\/\/arq.pciconcursos.com.br\/prefeitura-de-duque-de-caxias-rj-retifica-concurso-publico-com-400-vagas-para-guarda-civil-municipal\/1672641\/497f147634\/edital_de_abertura_n_01_2025_retificado_1672641.pdf"
            },
            {
                "titulo": "RETIFICAÇÃO I",
                "url": "https:\/\/arq.pciconcursos.com.br\/prefeitura-de-duque-de-caxias-rj-retifica-concurso-publico-com-400-vagas-para-guarda-civil-municipal\/1674878\/a0ae8bcf14\/retificacao_i_1674878.pdf"
            }
        ]
    },
    {
        "regiao": "RIO DE JANEIRO",
        "titulo": "Prefeitura de Niterói - (ION)",
        "link": "https:\/\/www.pciconcursos.com.br\/noticias\/prefeitura-de-niteroi-rj-retifica-concurso-publico-com-salarios-de-ate-12-mil",
        "imagem": "data:image\/png;base64,iVBORw0KGgoAAAANSUhEUgAAAAEAAAABCAYAAAAfFcSJAAAACXBIWXMAAA7EAAAOxAGVKw4bAAAADUlEQVQImWP4\/\/8\/AwAI\/AL+hc2rNAAAAABJRU5ErkJggg==",
        "resumo": "58 vagas até R$ 12.002,00 Vários Cargos Médio \/ Técnico \/ Superior",
        "periodo_inscricao": "Prorrogado até19\/06\/2025",
        "situacao": "Prorrogado",
        "link_apostila": [],
        "link_edital": [
            {
                "titulo": "EDITAL DE ABERTURA Nº 001\/2025",
                "url": "https:\/\/arq.pciconcursos.com.br\/prefeitura-de-niteroi-rj-retifica-concurso-publico-com-salarios-de-ate-12-mil\/1671432\/55db90c875\/edital_de_abertura_n_001_2025_1671432.pdf"
            },
            {
                "titulo": "RETIFICAÇÃO I",
                "url": "https:\/\/arq.pciconcursos.com.br\/prefeitura-de-niteroi-rj-retifica-concurso-publico-com-salarios-de-ate-12-mil\/1674509\/6c2dbf1c26\/retificacao_i_1674509.pdf"
            }
        ]
    },
    {
        "regiao": "RIO DE JANEIRO",
        "titulo": "UENF - Universidade Estadual do Norte Fluminense",
        "link": "https:\/\/www.pciconcursos.com.br\/noticias\/uenf-rj-abre-inscricoes-para-158-vagas-em-novo-concurso-publico-retificado",
        "imagem": "data:image\/png;base64,iVBORw0KGgoAAAANSUhEUgAAAAEAAAABCAYAAAAfFcSJAAAACXBIWXMAAA7EAAAOxAGVKw4bAAAADUlEQVQImWP4\/\/8\/AwAI\/AL+hc2rNAAAAABJRU5ErkJggg==",
        "resumo": "158 vagas até R$ 3938,79 Vários Cargos Médio \/ Técnico \/ Superior",
        "periodo_inscricao": "Prorrogado até23\/06\/2025",
        "situacao": "Prorrogado",
        "link_apostila": [],
        "link_edital": [
            {
                "titulo": "EDITAL DE ABERTURA Nº 01\/2025 - RETIFICADO",
                "url": "https:\/\/arq.pciconcursos.com.br\/uenf-rj-abre-inscricoes-para-158-vagas-em-novo-concurso-publico-retificado\/1674700\/2465ae0b3b\/edital_de_abertura_n_01_2025_retificado_1674700.pdf"
            },
            {
                "titulo": "RETIFICAÇÃO I",
                "url": "https:\/\/arq.pciconcursos.com.br\/uenf-rj-abre-inscricoes-para-158-vagas-em-novo-concurso-publico-retificado\/1675157\/459ef7df55\/retificacao_i_1675157.pdf"
            },
            {
                "titulo": "RETIFICAÇÃO II",
                "url": "https:\/\/arq.pciconcursos.com.br\/uenf-rj-abre-inscricoes-para-158-vagas-em-novo-concurso-publico-retificado\/1676057\/6d75307a5f\/retificacao_ii_1676057.pdf"
            }
        ]
    },
    {
        "regiao": "MINAS GERAIS",
        "titulo": "Câmara de Pompéu",
        "link": "https:\/\/www.pciconcursos.com.br\/noticias\/camara-de-pompeu-mg-promove-concurso-publico-para-agente-administrativo-e-assistente-social",
        "imagem": "data:image\/png;base64,iVBORw0KGgoAAAANSUhEUgAAAAEAAAABCAYAAAAfFcSJAAAACXBIWXMAAA7EAAAOxAGVKw4bAAAADUlEQVQImWP4\/\/8\/AwAI\/AL+hc2rNAAAAABJRU5ErkJggg==",
        "resumo": "6 vagas até R$ 5913,67 Agente Administrativo, Assistente Social Médio \/ Superior",
        "periodo_inscricao": "21\/07 a19\/08\/2025",
        "situacao": "Aberto",
        "link_apostila": [],
        "link_edital": [
            {
                "titulo": "EDITAL DE ABERTURA Nº 01\/2025",
                "url": "https:\/\/arq.pciconcursos.com.br\/camara-de-pompeu-mg-promove-concurso-publico-para-agente-administrativo-e-assistente-social\/1675229\/563d390e69\/edital_de_abertura_n_01_2025_1675229.pdf"
            }
        ]
    },
    {
        "regiao": "MINAS GERAIS",
        "titulo": "Câmara de Viçosa",
        "link": "https:\/\/www.pciconcursos.com.br\/noticias\/camara-de-vicosa-mg-retifica-concurso-publico-com-13-vagas",
        "imagem": "data:image\/png;base64,iVBORw0KGgoAAAANSUhEUgAAAAEAAAABCAYAAAAfFcSJAAAACXBIWXMAAA7EAAAOxAGVKw4bAAAADUlEQVQImWP4\/\/8\/AwAI\/AL+hc2rNAAAAABJRU5ErkJggg==",
        "resumo": "13 vagas até R$ 4587,63 Vários Cargos Médio \/ Superior",
        "periodo_inscricao": "12\/06 a14\/07\/2025",
        "situacao": "Aberto",
        "link_apostila": [],
        "link_edital": [
            {
                "titulo": "EDITAL DE ABERTURA Nº 01\/2025 - RETIFICADO",
                "url": "https:\/\/arq.pciconcursos.com.br\/camara-de-vicosa-mg-retifica-concurso-publico-com-13-vagas\/1672010\/7f510691ea\/edital_de_abertura_n_01_2025_retificado_1672010.pdf"
            },
            {
                "titulo": "RETIFICAÇÃO I",
                "url": "https:\/\/arq.pciconcursos.com.br\/camara-de-vicosa-mg-retifica-concurso-publico-com-13-vagas\/1674446\/5456c613b0\/retificacao_i_1674446.pdf"
            }
        ]
    },
    {
        "regiao": "MINAS GERAIS",
        "titulo": "FAPEMI - Instituto de Previdência Municipal de Itapeva",
        "link": "https:\/\/www.pciconcursos.com.br\/noticias\/fapemi-mg-promove-concurso-publico-para-auxiliar-administrativo",
        "imagem": "data:image\/png;base64,iVBORw0KGgoAAAANSUhEUgAAAAEAAAABCAYAAAAfFcSJAAAACXBIWXMAAA7EAAAOxAGVKw4bAAAADUlEQVQImWP4\/\/8\/AwAI\/AL+hc2rNAAAAABJRU5ErkJggg==",
        "resumo": "1 vaga até R$ 3339,40 Auxiliar Administrativo Superior",
        "periodo_inscricao": "02\/06 a02\/07\/2025",
        "situacao": "Aberto",
        "link_apostila": [],
        "link_edital": [
            {
                "titulo": "EDITAL DE ABERTURA Nº 01\/2025",
                "url": "https:\/\/arq.pciconcursos.com.br\/fapemi-mg-promove-concurso-publico-para-auxiliar-administrativo\/1671992\/4040958cbf\/edital_de_abertura_n_01_2025_1671992.pdf"
            }
        ]
    },
    {
        "regiao": "MINAS GERAIS",
        "titulo": "IFMG - Instituto Federal de Educação, Ciência e Tecnologia de Minas Gerais",
        "link": "https:\/\/www.pciconcursos.com.br\/noticias\/ifmg-abre-inscricoes-para-tres-concursos-publicos",
        "imagem": "data:image\/png;base64,iVBORw0KGgoAAAANSUhEUgAAAAEAAAABCAYAAAAfFcSJAAAACXBIWXMAAA7EAAAOxAGVKw4bAAAADUlEQVQImWP4\/\/8\/AwAI\/AL+hc2rNAAAAABJRU5ErkJggg==",
        "resumo": "7 vagas até R$ 5967,04 Vários Cargos Médio \/ Técnico \/ Superior",
        "periodo_inscricao": "30\/06\/2025",
        "situacao": "Inscrição não iniciada",
        "link_apostila": [],
        "link_edital": [
            {
                "titulo": "EDITAL DE ABERTURA Nº 374\/2025",
                "url": "https:\/\/arq.pciconcursos.com.br\/ifmg-abre-inscricoes-para-tres-concursos-publicos\/1674932\/6f0f7781e8\/edital_de_abertura_n_374_2025_1674932.pdf"
            },
            {
                "titulo": "EDITAL DE ABERTURA Nº 375\/2025",
                "url": "https:\/\/arq.pciconcursos.com.br\/ifmg-abre-inscricoes-para-tres-concursos-publicos\/1674933\/ee4cfb967a\/edital_de_abertura_n_375_2025_1674933.pdf"
            },
            {
                "titulo": "EDITAL DE ABERTURA Nº 426\/2025",
                "url": "https:\/\/arq.pciconcursos.com.br\/ifmg-abre-inscricoes-para-tres-concursos-publicos\/1674934\/b0d8d58a3b\/edital_de_abertura_n_426_2025_1674934.pdf"
            }
        ]
    },
    {
        "regiao": "MINAS GERAIS",
        "titulo": "Prefeitura de Belo Horizonte",
        "link": "https:\/\/www.pciconcursos.com.br\/noticias\/prefeitura-de-belo-horizonte-mg-divulga-concurso-publico-com-582-vagas",
        "imagem": "data:image\/png;base64,iVBORw0KGgoAAAANSUhEUgAAAAEAAAABCAYAAAAfFcSJAAAACXBIWXMAAA7EAAAOxAGVKw4bAAAADUlEQVQImWP4\/\/8\/AwAI\/AL+hc2rNAAAAABJRU5ErkJggg==",
        "resumo": "582 vagas até R$ 11.747,78 Vários Cargos Técnico \/ Superior",
        "periodo_inscricao": "02\/06 a02\/07\/2025",
        "situacao": "Aberto",
        "link_apostila": [],
        "link_edital": [
            {
                "titulo": "EDITAL DE ABERTURA Nº 01\/2025",
                "url": "https:\/\/arq.pciconcursos.com.br\/prefeitura-de-belo-horizonte-mg-divulga-concurso-publico-com-582-vagas\/1671707\/5a7c412690\/edital_de_abertura_n_01_2025_1671707.pdf"
            }
        ]
    },
    {
        "regiao": "MINAS GERAIS",
        "titulo": "Prefeitura de Estrela Dalva",
        "link": "https:\/\/www.pciconcursos.com.br\/noticias\/prefeitura-de-estrela-dalva-mg-republica-editais-de-concurso-publico-e-processo-seletivo",
        "imagem": "data:image\/png;base64,iVBORw0KGgoAAAANSUhEUgAAAAEAAAABCAYAAAAfFcSJAAAACXBIWXMAAA7EAAAOxAGVKw4bAAAADUlEQVQImWP4\/\/8\/AwAI\/AL+hc2rNAAAAABJRU5ErkJggg==",
        "resumo": "95 vagas até R$ 4566,27 Vários Cargos Fundamental \/ Médio \/ Técnico \/ Superior",
        "periodo_inscricao": "28\/07 a28\/08\/2025",
        "situacao": "Aberto",
        "link_apostila": [],
        "link_edital": [
            {
                "titulo": "EDITAL DE ABERTURA Nº 01\/2025 (CONCURSO PÚBLICO) - REPUBLICADO",
                "url": "https:\/\/arq.pciconcursos.com.br\/prefeitura-de-estrela-dalva-mg-republica-editais-de-concurso-publico-e-processo-seletivo\/1675000\/d5687e25ae\/edital_de_abertura_n_01_2025_concurso_publico_republicado_1675000.pdf"
            },
            {
                "titulo": "EDITAL DE ABERTURA Nº 02\/2025 (PROCESSO SELETIVO) - REPUBLICADO",
                "url": "https:\/\/arq.pciconcursos.com.br\/prefeitura-de-estrela-dalva-mg-republica-editais-de-concurso-publico-e-processo-seletivo\/1675001\/aa8d863837\/edital_de_abertura_n_02_2025_processo_seletivo_republicado_1675001.pdf"
            }
        ]
    },
    {
        "regiao": "MINAS GERAIS",
        "titulo": "Prefeitura de Paracatu",
        "link": "https:\/\/www.pciconcursos.com.br\/noticias\/prefeitura-de-paracatu-mg-retifica-processo-seletivo-com-51-vagas-para-agentes-comunitarios-de-saude",
        "imagem": "data:image\/png;base64,iVBORw0KGgoAAAANSUhEUgAAAAEAAAABCAYAAAAfFcSJAAAACXBIWXMAAA7EAAAOxAGVKw4bAAAADUlEQVQImWP4\/\/8\/AwAI\/AL+hc2rNAAAAABJRU5ErkJggg==",
        "resumo": "51 vagas até R$ 2824,80 Agente Comunitário de Saúde Ensino Médio",
        "periodo_inscricao": "03\/06 a07\/07\/2025",
        "situacao": "Aberto",
        "link_apostila": [],
        "link_edital": [
            {
                "titulo": "EDITAL DE ABERTURA Nº 01\/2025 - RETIFICADO",
                "url": "https:\/\/arq.pciconcursos.com.br\/prefeitura-de-paracatu-mg-retifica-processo-seletivo-com-51-vagas-para-agentes-comunitarios-de-saude\/1671413\/7cd4c849ac\/edital_de_abertura_n_01_2025_retificado_1671413.pdf"
            },
            {
                "titulo": "RETIFICAÇÃO I",
                "url": "https:\/\/arq.pciconcursos.com.br\/prefeitura-de-paracatu-mg-retifica-processo-seletivo-com-51-vagas-para-agentes-comunitarios-de-saude\/1676153\/4f87af33d4\/retificacao_i_1676153.pdf"
            }
        ]
    },
    {
        "regiao": "MINAS GERAIS",
        "titulo": "Prefeitura de Serrania",
        "link": "https:\/\/www.pciconcursos.com.br\/noticias\/prefeitura-de-serrania-mg-retifica-dois-concursos-publicos-com-47-vagas",
        "imagem": "data:image\/png;base64,iVBORw0KGgoAAAANSUhEUgAAAAEAAAABCAYAAAAfFcSJAAAACXBIWXMAAA7EAAAOxAGVKw4bAAAADUlEQVQImWP4\/\/8\/AwAI\/AL+hc2rNAAAAABJRU5ErkJggg==",
        "resumo": "47 vagas até R$ 13.401,70 Vários Cargos Fundamental \/ Médio \/ Técnico \/ Superior",
        "periodo_inscricao": "Reaberto até23\/06\/2025",
        "situacao": "Indefinido",
        "link_apostila": [],
        "link_edital": [
            {
                "titulo": "EDITAL DE ABERTURA Nº 01\/2024 - RETIFICADO",
                "url": "https:\/\/arq.pciconcursos.com.br\/prefeitura-de-serrania-mg-retifica-dois-concursos-publicos-com-47-vagas\/1661592\/2c20845f42\/edital_de_abertura_n_01_2024_retificado_1661592.pdf"
            },
            {
                "titulo": "RETIFICAÇÃO II - EDITAL DE ABERTURA Nº 01\/2024",
                "url": "https:\/\/arq.pciconcursos.com.br\/prefeitura-de-serrania-mg-retifica-dois-concursos-publicos-com-47-vagas\/1670745\/78d6f27a30\/retificacao_ii_edital_de_abertura_n_01_2024_1670745.pdf"
            },
            {
                "titulo": "RETIFICAÇÃO I - EDITAL DE ABERTURA Nº 01\/2024",
                "url": "https:\/\/arq.pciconcursos.com.br\/prefeitura-de-serrania-mg-retifica-dois-concursos-publicos-com-47-vagas\/1668093\/e62da9572c\/retificacao_i_edital_de_abertura_n_01_2024_1668093.pdf"
            },
            {
                "titulo": "EDITAL DE ABERTURA Nº 02\/2024 - RETIFICADO",
                "url": "https:\/\/arq.pciconcursos.com.br\/prefeitura-de-serrania-mg-retifica-dois-concursos-publicos-com-47-vagas\/1661593\/f1374b911e\/edital_de_abertura_n_02_2024_retificado_1661593.pdf"
            },
            {
                "titulo": "RETIFICAÇÃO I - EDITAL DE ABERTURA Nº 02\/2024",
                "url": "https:\/\/arq.pciconcursos.com.br\/prefeitura-de-serrania-mg-retifica-dois-concursos-publicos-com-47-vagas\/1668094\/8fe1084a2e\/retificacao_i_edital_de_abertura_n_02_2024_1668094.pdf"
            },
            {
                "titulo": "RETIFICAÇÃO II - EDITAL DE ABERTURA Nº 02\/2024",
                "url": "https:\/\/arq.pciconcursos.com.br\/prefeitura-de-serrania-mg-retifica-dois-concursos-publicos-com-47-vagas\/1670746\/6fed9f2cda\/retificacao_ii_edital_de_abertura_n_02_2024_1670746.pdf"
            }
        ]
    },
    {
        "regiao": "MINAS GERAIS",
        "titulo": "Prefeitura de Uberaba",
        "link": "https:\/\/www.pciconcursos.com.br\/noticias\/prefeitura-de-uberaba-mg-informa-abertura-de-processo-seletivo-com-81-vagas",
        "imagem": "data:image\/png;base64,iVBORw0KGgoAAAANSUhEUgAAAAEAAAABCAYAAAAfFcSJAAAACXBIWXMAAA7EAAAOxAGVKw4bAAAADUlEQVQImWP4\/\/8\/AwAI\/AL+hc2rNAAAAABJRU5ErkJggg==",
        "resumo": "81 vagas até R$ 3036,00 Agente Comunitário de Saúde Ensino Médio",
        "periodo_inscricao": "07\/07 a07\/08\/2025",
        "situacao": "Aberto",
        "link_apostila": [],
        "link_edital": [
            {
                "titulo": "EDITAL DE ABERTURA Nº 01\/2025",
                "url": "https:\/\/arq.pciconcursos.com.br\/prefeitura-de-uberaba-mg-informa-abertura-de-processo-seletivo-com-81-vagas\/1674363\/36d5d3c99a\/edital_de_abertura_n_01_2025_1674363.pdf"
            }
        ]
    },
    {
        "regiao": "MINAS GERAIS",
        "titulo": "SEE - Secretaria de Estado de Educação de Minas Gerais",
        "link": "https:\/\/www.pciconcursos.com.br\/noticias\/see-mg-e-seplag-abrem-edital-de-concurso-publico-com-13795-vagas",
        "imagem": "data:image\/png;base64,iVBORw0KGgoAAAANSUhEUgAAAAEAAAABCAYAAAAfFcSJAAAACXBIWXMAAA7EAAAOxAGVKw4bAAAADUlEQVQImWP4\/\/8\/AwAI\/AL+hc2rNAAAAABJRU5ErkJggg==",
        "resumo": "13.795 vagas até R$ 6937,06 Vários Cargos Médio \/ Técnico \/ Superior",
        "periodo_inscricao": "21\/07 a21\/08\/2025",
        "situacao": "Aberto",
        "link_apostila": [],
        "link_edital": [
            {
                "titulo": "EDITAL DE ABERTURA Nº 01\/2025",
                "url": "https:\/\/arq.pciconcursos.com.br\/see-mg-e-seplag-abrem-edital-de-concurso-publico-com-13795-vagas\/1675153\/2ce0ebe365\/edital_de_abertura_n_01_2025_1675153.pdf"
            }
        ]
    },
    {
        "regiao": "PARANÁ",
        "titulo": "Polícia Militar do Paraná",
        "link": "https:\/\/www.pciconcursos.com.br\/noticias\/pm-pr-divulga-retificacao-de-concurso-publico-com-90-vagas-para-cadetes",
        "imagem": "data:image\/png;base64,iVBORw0KGgoAAAANSUhEUgAAAAEAAAABCAYAAAAfFcSJAAAACXBIWXMAAA7EAAAOxAGVKw4bAAAADUlEQVQImWP4\/\/8\/AwAI\/AL+hc2rNAAAAABJRU5ErkJggg==",
        "resumo": "90 vagas até R$ 13.731,61 Cadete da PMSuperior",
        "periodo_inscricao": "09\/06\/2025",
        "situacao": "Inscrição não iniciada",
        "link_apostila": [],
        "link_edital": [
            {
                "titulo": "EDITAL DE ABERTURA Nº 01\/2025 - RETIFICADO",
                "url": "https:\/\/arq.pciconcursos.com.br\/pm-pr-divulga-retificacao-de-concurso-publico-com-90-vagas-para-cadetes\/1673112\/bd9dfed5fc\/edital_de_abertura_n_01_2025_retificado_1673112.pdf"
            },
            {
                "titulo": "RETIFICAÇÃO I",
                "url": "https:\/\/arq.pciconcursos.com.br\/pm-pr-divulga-retificacao-de-concurso-publico-com-90-vagas-para-cadetes\/1673731\/62034f8908\/retificacao_i_1673731.pdf"
            }
        ]
    },
    {
        "regiao": "PARANÁ",
        "titulo": "TJ - Tribunal de Justiça do Estado do Paraná",
        "link": "https:\/\/www.pciconcursos.com.br\/noticias\/tj-pr-abre-concurso-publico-para-tecnico-judiciario",
        "imagem": "data:image\/png;base64,iVBORw0KGgoAAAANSUhEUgAAAAEAAAABCAYAAAAfFcSJAAAACXBIWXMAAA7EAAAOxAGVKw4bAAAADUlEQVQImWP4\/\/8\/AwAI\/AL+hc2rNAAAAABJRU5ErkJggg==",
        "resumo": "60 vagas até R$ 9582,99 Técnico Judiciário Ensino Médio",
        "periodo_inscricao": "07\/07\/2025",
        "situacao": "Inscrição não iniciada",
        "link_apostila": [],
        "link_edital": [
            {
                "titulo": "EDITAL DE ABERTURA Nº 06\/2025",
                "url": "https:\/\/arq.pciconcursos.com.br\/tj-pr-abre-concurso-publico-para-tecnico-judiciario\/1675889\/5469993656\/edital_de_abertura_n_06_2025_1675889.pdf"
            }
        ]
    },
    {
        "regiao": "RIO GRANDE DO SUL",
        "titulo": "AGESAN - Agência Reguladora Intermunicipal de Saneamento do Estado do Rio Grande do Sul",
        "link": "https:\/\/www.pciconcursos.com.br\/noticias\/agesan-rs-retifica-e-prorroga-concurso-publico",
        "imagem": "data:image\/png;base64,iVBORw0KGgoAAAANSUhEUgAAAAEAAAABCAYAAAAfFcSJAAAACXBIWXMAAA7EAAAOxAGVKw4bAAAADUlEQVQImWP4\/\/8\/AwAI\/AL+hc2rNAAAAABJRU5ErkJggg==",
        "resumo": "11 vagas até R$ 7827,78 Vários Cargos Médio \/ Superior",
        "periodo_inscricao": "Prorrogado até25\/06\/2025",
        "situacao": "Prorrogado",
        "link_apostila": [],
        "link_edital": [
            {
                "titulo": "EDITAL DE ABERTURA Nº 01\/2025 - RETIFICADO",
                "url": "https:\/\/arq.pciconcursos.com.br\/agesan-rs-retifica-e-prorroga-concurso-publico\/1674531\/096d055664\/edital_de_abertura_n_01_2025_retificado_1674531.pdf"
            },
            {
                "titulo": "RETIFICAÇÃO I",
                "url": "https:\/\/arq.pciconcursos.com.br\/agesan-rs-retifica-e-prorroga-concurso-publico\/1674811\/cd5545c64d\/retificacao_i_1674811.pdf"
            },
            {
                "titulo": "RETIFICAÇÃO II",
                "url": "https:\/\/arq.pciconcursos.com.br\/agesan-rs-retifica-e-prorroga-concurso-publico\/1676166\/08060f23c7\/retificacao_ii_1676166.pdf"
            }
        ]
    },
    {
        "regiao": "GOIÁS",
        "titulo": "Prefeitura de Goiás",
        "link": "https:\/\/www.pciconcursos.com.br\/noticias\/prefeitura-de-goias-go-retifica-concurso-publico-com-salarios-de-ate-3-1-mil",
        "imagem": "data:image\/png;base64,iVBORw0KGgoAAAANSUhEUgAAAAEAAAABCAYAAAAfFcSJAAAACXBIWXMAAA7EAAAOxAGVKw4bAAAADUlEQVQImWP4\/\/8\/AwAI\/AL+hc2rNAAAAABJRU5ErkJggg==",
        "resumo": "79 vagas até R$ 3155,67 Vários Cargos Médio \/ Técnico \/ Superior",
        "periodo_inscricao": "09\/06 a07\/07\/2025",
        "situacao": "Aberto",
        "link_apostila": [],
        "link_edital": [
            {
                "titulo": "EDITAL DE ABERTURA Nº 01\/2025 - RETIFICADO",
                "url": "https:\/\/arq.pciconcursos.com.br\/prefeitura-de-goias-go-retifica-concurso-publico-com-salarios-de-ate-3-1-mil\/1674170\/72f64f6803\/edital_de_abertura_n_01_2025_retificado_1674170.pdf"
            },
            {
                "titulo": "RETIFICAÇÃO I",
                "url": "https:\/\/arq.pciconcursos.com.br\/prefeitura-de-goias-go-retifica-concurso-publico-com-salarios-de-ate-3-1-mil\/1675064\/1485b02159\/retificacao_i_1675064.pdf"
            }
        ]
    },
    {
        "regiao": "MATO GROSSO",
        "titulo": "ARIS Agência Reguladora Intermunicipal de Saneamento do Estado de Mato Grosso",
        "link": "https:\/\/www.pciconcursos.com.br\/noticias\/aris-mt-divulga-concurso-publico-com-salarios-de-ate-6-5-mil",
        "imagem": "data:image\/png;base64,iVBORw0KGgoAAAANSUhEUgAAAAEAAAABCAYAAAAfFcSJAAAACXBIWXMAAA7EAAAOxAGVKw4bAAAADUlEQVQImWP4\/\/8\/AwAI\/AL+hc2rNAAAAABJRU5ErkJggg==",
        "resumo": "7 vagas até R$ 6539,08 Vários Cargos Médio \/ Superior",
        "periodo_inscricao": "09\/06\/2025",
        "situacao": "Inscrição não iniciada",
        "link_apostila": [],
        "link_edital": [
            {
                "titulo": "EDITAL DE ABERTURA Nº 01\/2025",
                "url": "https:\/\/arq.pciconcursos.com.br\/aris-mt-divulga-concurso-publico-com-salarios-de-ate-6-5-mil\/1673845\/fd240783cf\/edital_de_abertura_n_01_2025_1673845.pdf"
            }
        ]
    },
    {
        "regiao": "PARÁ",
        "titulo": "Prefeitura de Marituba",
        "link": "https:\/\/www.pciconcursos.com.br\/noticias\/prefeitura-de-marituba-pa-retifica-concurso-publico-para-guarda-civil",
        "imagem": "data:image\/png;base64,iVBORw0KGgoAAAANSUhEUgAAAAEAAAABCAYAAAAfFcSJAAAACXBIWXMAAA7EAAAOxAGVKw4bAAAADUlEQVQImWP4\/\/8\/AwAI\/AL+hc2rNAAAAABJRU5ErkJggg==",
        "resumo": "60 vagas até R$ 1800,00 Guarda Civil Ensino Médio",
        "periodo_inscricao": "13\/06\/2025",
        "situacao": "Inscrição não iniciada",
        "link_apostila": [],
        "link_edital": [
            {
                "titulo": "EDITAL DE ABERTURA Nº 01\/2025",
                "url": "https:\/\/arq.pciconcursos.com.br\/prefeitura-de-marituba-pa-retifica-concurso-publico-para-guarda-civil\/1673575\/a281f92751\/edital_de_abertura_n_01_2025_1673575.pdf"
            },
            {
                "titulo": "RETIFICAÇÃO I",
                "url": "https:\/\/arq.pciconcursos.com.br\/prefeitura-de-marituba-pa-retifica-concurso-publico-para-guarda-civil\/1673921\/175ac280e2\/retificacao_i_1673921.pdf"
            }
        ]
    },
    {
        "regiao": "PARÁ",
        "titulo": "Prefeitura de Piçarra",
        "link": "https:\/\/www.pciconcursos.com.br\/noticias\/prefeitura-de-picarra-pa-abre-270-vagas-em-novo-concurso-publico-retificado",
        "imagem": "data:image\/png;base64,iVBORw0KGgoAAAANSUhEUgAAAAEAAAABCAYAAAAfFcSJAAAACXBIWXMAAA7EAAAOxAGVKw4bAAAADUlEQVQImWP4\/\/8\/AwAI\/AL+hc2rNAAAAABJRU5ErkJggg==",
        "resumo": "270 vagas até R$ 4750,00 Vários Cargos Fundamental \/ Médio \/ Técnico \/ Superior",
        "periodo_inscricao": "02\/06\/2025",
        "situacao": "Inscrição não iniciada",
        "link_apostila": [],
        "link_edital": [
            {
                "titulo": "EDITAL DE ABERTURA Nº 001\/2025",
                "url": "https:\/\/arq.pciconcursos.com.br\/prefeitura-de-picarra-pa-abre-270-vagas-em-novo-concurso-publico-retificado\/1673762\/e7ad28c252\/edital_de_abertura_n_001_2025_1673762.pdf"
            },
            {
                "titulo": "RETIFICAÇÃO I",
                "url": "https:\/\/arq.pciconcursos.com.br\/prefeitura-de-picarra-pa-abre-270-vagas-em-novo-concurso-publico-retificado\/1674213\/fa75f2cc24\/retificacao_i_1674213.pdf"
            }
        ]
    },
    {
        "regiao": "ALAGOAS",
        "titulo": "Prefeitura de Japaratinga",
        "link": "https:\/\/www.pciconcursos.com.br\/noticias\/prefeitura-de-japaratinga-al-divulga-edital-retificado-de-concurso-publico",
        "imagem": "data:image\/png;base64,iVBORw0KGgoAAAANSUhEUgAAAAEAAAABCAYAAAAfFcSJAAAACXBIWXMAAA7EAAAOxAGVKw4bAAAADUlEQVQImWP4\/\/8\/AwAI\/AL+hc2rNAAAAABJRU5ErkJggg==",
        "resumo": "134 vagas até R$ 4000,00 Vários Cargos Fundamental \/ Médio \/ Técnico \/ Superior",
        "periodo_inscricao": "Prorrogado até06\/07\/2025",
        "situacao": "Prorrogado",
        "link_apostila": [],
        "link_edital": [
            {
                "titulo": "EDITAL DE ABERTURA Nº 01\/2025 - RETIFICADO",
                "url": "https:\/\/arq.pciconcursos.com.br\/prefeitura-de-japaratinga-al-divulga-edital-retificado-de-concurso-publico\/1673129\/4bd7c1c4ea\/edital_de_abertura_n_01_2025_retificado_1673129.pdf"
            }
        ]
    },
    {
        "regiao": "BAHIA",
        "titulo": "Câmara de Caetité",
        "link": "https:\/\/www.pciconcursos.com.br\/noticias\/camara-municipal-de-caetite-ba-retifica-concurso-publico-com-10-vagas",
        "imagem": "data:image\/png;base64,iVBORw0KGgoAAAANSUhEUgAAAAEAAAABCAYAAAAfFcSJAAAACXBIWXMAAA7EAAAOxAGVKw4bAAAADUlEQVQImWP4\/\/8\/AwAI\/AL+hc2rNAAAAABJRU5ErkJggg==",
        "resumo": "16 vagas até R$ 5000,00 Vários Cargos Fundamental \/ Médio",
        "periodo_inscricao": "Prorrogado de19\/06 a18\/07\/2025",
        "situacao": "Aberto",
        "link_apostila": [],
        "link_edital": [
            {
                "titulo": "EDITAL DE ABERTURA RETIFICADO Nº 01\/2024",
                "url": "https:\/\/arq.pciconcursos.com.br\/camara-municipal-de-caetite-ba-retifica-concurso-publico-com-10-vagas\/1659124\/e49203dbeb\/edital_de_abertura_retificado_n_01_2024_1659124.pdf"
            },
            {
                "titulo": "RETIFICAÇÃO I",
                "url": "https:\/\/arq.pciconcursos.com.br\/camara-municipal-de-caetite-ba-retifica-concurso-publico-com-10-vagas\/1661758\/2c6357f0d4\/retificacao_i_1661758.pdf"
            },
            {
                "titulo": "RETIFICAÇÃO II",
                "url": "https:\/\/arq.pciconcursos.com.br\/camara-municipal-de-caetite-ba-retifica-concurso-publico-com-10-vagas\/1662886\/ce869e65ee\/retificacao_ii_1662886.pdf"
            },
            {
                "titulo": "RETIFICAÇÃO III",
                "url": "https:\/\/arq.pciconcursos.com.br\/camara-municipal-de-caetite-ba-retifica-concurso-publico-com-10-vagas\/1667583\/c9d80f2d2b\/retificacao_iii_1667583.pdf"
            },
            {
                "titulo": "RETIFICAÇÃO IV",
                "url": "https:\/\/arq.pciconcursos.com.br\/camara-municipal-de-caetite-ba-retifica-concurso-publico-com-10-vagas\/1667798\/70887f74cc\/retificacao_iv_1667798.pdf"
            },
            {
                "titulo": "RETIFICAÇÃO V",
                "url": "https:\/\/arq.pciconcursos.com.br\/camara-municipal-de-caetite-ba-retifica-concurso-publico-com-10-vagas\/1668657\/fce0221792\/retificacao_v_1668657.pdf"
            }
        ]
    },
    {
        "regiao": "CEARÁ",
        "titulo": "Autarquia Municipal de Trânsito de Eusébio",
        "link": "https:\/\/www.pciconcursos.com.br\/noticias\/autarquia-municipal-de-transito-de-eusebio-ce-abre-inscricoes-para-novo-concurso-publico",
        "imagem": "data:image\/png;base64,iVBORw0KGgoAAAANSUhEUgAAAAEAAAABCAYAAAAfFcSJAAAACXBIWXMAAA7EAAAOxAGVKw4bAAAADUlEQVQImWP4\/\/8\/AwAI\/AL+hc2rNAAAAABJRU5ErkJggg==",
        "resumo": "10 vagas até R$ 1518,00 Agente Municipal de Trânsito Ensino Médio",
        "periodo_inscricao": "01\/06\/2025",
        "situacao": "Fechado",
        "link_apostila": [],
        "link_edital": [
            {
                "titulo": "EDITAL DE ABERTURA Nº 001\/2025",
                "url": "https:\/\/arq.pciconcursos.com.br\/autarquia-municipal-de-transito-de-eusebio-ce-abre-inscricoes-para-novo-concurso-publico\/1674572\/714c7e5cb2\/edital_de_abertura_n_001_2025_1674572.pdf"
            }
        ]
    },
    {
        "regiao": "CEARÁ",
        "titulo": "CBMCE - Corpo de Bombeiros Militar do Estado do Ceará",
        "link": "https:\/\/www.pciconcursos.com.br\/noticias\/sspds-aesp-e-seplag-ce-divulgam-concurso-publico-para-soldado-do-quadro-de-pracas-bombeiros-militares",
        "imagem": "data:image\/png;base64,iVBORw0KGgoAAAANSUhEUgAAAAEAAAABCAYAAAAfFcSJAAAACXBIWXMAAA7EAAAOxAGVKw4bAAAADUlEQVQImWP4\/\/8\/AwAI\/AL+hc2rNAAAAABJRU5ErkJggg==",
        "resumo": "450 vagas até R$ 5893,30 Soldado QPBMEnsino Médio",
        "periodo_inscricao": "02\/06\/2025",
        "situacao": "Inscrição não iniciada",
        "link_apostila": [],
        "link_edital": [
            {
                "titulo": "EDITAL DE ABERTURA Nº 01\/2025",
                "url": "https:\/\/arq.pciconcursos.com.br\/sspds-aesp-e-seplag-ce-divulgam-concurso-publico-para-soldado-do-quadro-de-pracas-bombeiros-militares\/1673804\/6b38d35d07\/edital_de_abertura_n_01_2025_1673804.pdf"
            }
        ]
    },
    {
        "regiao": "MARANHÃO",
        "titulo": "Prefeitura de Barra do Corda",
        "link": "https:\/\/www.pciconcursos.com.br\/noticias\/prefeitura-de-barra-do-corda-ma-retifica-dois-editais-de-concurso-publico",
        "imagem": "data:image\/png;base64,iVBORw0KGgoAAAANSUhEUgAAAAEAAAABCAYAAAAfFcSJAAAACXBIWXMAAA7EAAAOxAGVKw4bAAAADUlEQVQImWP4\/\/8\/AwAI\/AL+hc2rNAAAAABJRU5ErkJggg==",
        "resumo": "284 vagas até R$ 8000,00 Vários Cargos Fundamental \/ Médio \/ Técnico \/ Superior",
        "periodo_inscricao": "16\/06\/2025",
        "situacao": "Inscrição não iniciada",
        "link_apostila": [],
        "link_edital": [
            {
                "titulo": "EDITAL DE ABERTURA Nº 01\/2025 - RETIFICADO",
                "url": "https:\/\/arq.pciconcursos.com.br\/prefeitura-de-barra-do-corda-ma-retifica-dois-editais-de-concurso-publico\/1674796\/a30f78d22a\/edital_de_abertura_n_01_2025_retificado_1674796.pdf"
            },
            {
                "titulo": "RETIFICAÇÃO I - EDITAL DE ABERTURA Nº 01\/2025",
                "url": "https:\/\/arq.pciconcursos.com.br\/prefeitura-de-barra-do-corda-ma-retifica-dois-editais-de-concurso-publico\/1675806\/49bb929466\/retificacao_i_edital_de_abertura_n_01_2025_1675806.pdf"
            },
            {
                "titulo": "EDITAL DE ABERTURA Nº 02\/2025 - RETIFICADO",
                "url": "https:\/\/arq.pciconcursos.com.br\/prefeitura-de-barra-do-corda-ma-retifica-dois-editais-de-concurso-publico\/1674797\/4581275878\/edital_de_abertura_n_02_2025_retificado_1674797.pdf"
            }
        ]
    },
    {
        "regiao": "PARAÍBA",
        "titulo": "Prefeitura de João Pessoa",
        "link": "https:\/\/www.pciconcursos.com.br\/noticias\/prefeitura-de-joao-pessoa-pb-prorroga-e-retifica-edital-de-concurso-publico",
        "imagem": "data:image\/png;base64,iVBORw0KGgoAAAANSUhEUgAAAAEAAAABCAYAAAAfFcSJAAAACXBIWXMAAA7EAAAOxAGVKw4bAAAADUlEQVQImWP4\/\/8\/AwAI\/AL+hc2rNAAAAABJRU5ErkJggg==",
        "resumo": "403 vagas até R$ 4567,31 Vários Cargos Superior",
        "periodo_inscricao": "Prorrogado até02\/06\/2025",
        "situacao": "Prorrogado",
        "link_apostila": [],
        "link_edital": [
            {
                "titulo": "EDITAL DE ABERTURA Nº 01\/2025",
                "url": "https:\/\/arq.pciconcursos.com.br\/prefeitura-de-joao-pessoa-pb-prorroga-e-retifica-edital-de-concurso-publico\/1672918\/5f823574de\/edital_de_abertura_n_01_2025_1672918.pdf"
            },
            {
                "titulo": "PRORROGAÇÃO",
                "url": "https:\/\/arq.pciconcursos.com.br\/prefeitura-de-joao-pessoa-pb-prorroga-e-retifica-edital-de-concurso-publico\/1675179\/5751262fdc\/prorrogacao_1675179.pdf"
            },
            {
                "titulo": "RETIFICAÇÃO I",
                "url": "https:\/\/arq.pciconcursos.com.br\/prefeitura-de-joao-pessoa-pb-prorroga-e-retifica-edital-de-concurso-publico\/1675180\/427b612e4a\/retificacao_i_1675180.pdf"
            }
        ]
    },
    {
        "regiao": "PARAÍBA",
        "titulo": "SECULT - Secretaria da Cultura do Estado",
        "link": "https:\/\/www.pciconcursos.com.br\/noticias\/governo-do-estado-da-paraiba-abre-33-vagas-em-novo-concurso-publico",
        "imagem": "data:image\/png;base64,iVBORw0KGgoAAAANSUhEUgAAAAEAAAABCAYAAAAfFcSJAAAACXBIWXMAAA7EAAAOxAGVKw4bAAAADUlEQVQImWP4\/\/8\/AwAI\/AL+hc2rNAAAAABJRU5ErkJggg==",
        "resumo": "33 vagas até R$ 3500,00 Vários Cargos Superior",
        "periodo_inscricao": "23\/06\/2025",
        "situacao": "Inscrição não iniciada",
        "link_apostila": [],
        "link_edital": [
            {
                "titulo": "EDITAL DE ABERTURA Nº 01\/2025",
                "url": "https:\/\/arq.pciconcursos.com.br\/governo-do-estado-da-paraiba-abre-33-vagas-em-novo-concurso-publico\/1675384\/ddd0a05ab8\/edital_de_abertura_n_01_2025_1675384.pdf"
            }
        ]
    },
    {
        "regiao": "PERNAMBUCO",
        "titulo": "Prefeitura de Caruaru",
        "link": "https:\/\/www.pciconcursos.com.br\/noticias\/prefeitura-de-caruaru-pe-prorroga-inscricoes-de-concursos-publicos",
        "imagem": "data:image\/png;base64,iVBORw0KGgoAAAANSUhEUgAAAAEAAAABCAYAAAAfFcSJAAAACXBIWXMAAA7EAAAOxAGVKw4bAAAADUlEQVQImWP4\/\/8\/AwAI\/AL+hc2rNAAAAABJRU5ErkJggg==",
        "resumo": "36 vagas até R$ 5000,00 Vários Cargos Médio \/ Técnico \/ Superior",
        "periodo_inscricao": "Prorrogado até03\/06\/2025",
        "situacao": "Prorrogado",
        "link_apostila": [],
        "link_edital": [
            {
                "titulo": "EDITAL DE ABERTURA Nº 01\/2025",
                "url": "https:\/\/arq.pciconcursos.com.br\/prefeitura-de-caruaru-pe-prorroga-inscricoes-de-concursos-publicos\/1671667\/1029970977\/edital_de_abertura_n_01_2025_1671667.pdf"
            },
            {
                "titulo": "EDITAL DE ABERTURA Nº 02\/2025",
                "url": "https:\/\/arq.pciconcursos.com.br\/prefeitura-de-caruaru-pe-prorroga-inscricoes-de-concursos-publicos\/1671668\/47a07019aa\/edital_de_abertura_n_02_2025_1671668.pdf"
            },
            {
                "titulo": "PRORROGAÇÃO - EDITAL Nº 01\/2025",
                "url": "https:\/\/arq.pciconcursos.com.br\/prefeitura-de-caruaru-pe-prorroga-inscricoes-de-concursos-publicos\/1675245\/e0640f7cbb\/prorrogacao_edital_n_01_2025_1675245.pdf"
            },
            {
                "titulo": "PRORROGAÇÃO - EDITAL Nº 02\/2025",
                "url": "https:\/\/arq.pciconcursos.com.br\/prefeitura-de-caruaru-pe-prorroga-inscricoes-de-concursos-publicos\/1675246\/1f96ec3df7\/prorrogacao_edital_n_02_2025_1675246.pdf"
            }
        ]
    },
    {
        "regiao": "RIO GRANDE DO NORTE",
        "titulo": "EMPARN - Empresa de Pesquisa Agropecuária do Rio Grande do Norte",
        "link": "https:\/\/www.pciconcursos.com.br\/noticias\/emparn-prorroga-inscricoes-de-concurso-publico-com-salarios-de-ate-9-7-mil",
        "imagem": "data:image\/png;base64,iVBORw0KGgoAAAANSUhEUgAAAAEAAAABCAYAAAAfFcSJAAAACXBIWXMAAA7EAAAOxAGVKw4bAAAADUlEQVQImWP4\/\/8\/AwAI\/AL+hc2rNAAAAABJRU5ErkJggg==",
        "resumo": "16 vagas até R$ 9714,41 Vários Cargos Técnico \/ Superior",
        "periodo_inscricao": "Prorrogado até02\/06\/2025",
        "situacao": "Prorrogado",
        "link_apostila": [],
        "link_edital": [
            {
                "titulo": "EDITAL DE ABERTURA Nº 01\/2025",
                "url": "https:\/\/arq.pciconcursos.com.br\/emparn-prorroga-inscricoes-de-concurso-publico-com-salarios-de-ate-9-7-mil\/1672260\/5847923d68\/edital_de_abertura_n_01_2025_1672260.pdf"
            },
            {
                "titulo": "RETIFICAÇÃO I",
                "url": "https:\/\/arq.pciconcursos.com.br\/emparn-prorroga-inscricoes-de-concurso-publico-com-salarios-de-ate-9-7-mil\/1674535\/f698175248\/retificacao_i_1674535.pdf"
            },
            {
                "titulo": "RETIFICAÇÃO II",
                "url": "https:\/\/arq.pciconcursos.com.br\/emparn-prorroga-inscricoes-de-concurso-publico-com-salarios-de-ate-9-7-mil\/1675316\/6bc03a8ad1\/retificacao_ii_1675316.pdf"
            }
        ]
    },
    {
        "regiao": "RIO GRANDE DO NORTE",
        "titulo": "IDEMA - Instituto de Desenvolvimento Sustentável e Meio Ambiente",
        "link": "https:\/\/www.pciconcursos.com.br\/noticias\/sead-e-idema-rn-divulgam-concurso-publico-com-180-vagas",
        "imagem": "data:image\/png;base64,iVBORw0KGgoAAAANSUhEUgAAAAEAAAABCAYAAAAfFcSJAAAACXBIWXMAAA7EAAAOxAGVKw4bAAAADUlEQVQImWP4\/\/8\/AwAI\/AL+hc2rNAAAAABJRU5ErkJggg==",
        "resumo": "180 vagas até R$ 5118,52 Vários Cargos Superior",
        "periodo_inscricao": "06\/06\/2025",
        "situacao": "Inscrição não iniciada",
        "link_apostila": [],
        "link_edital": [
            {
                "titulo": "EDITAL DE ABERTURA Nº 04\/2025",
                "url": "https:\/\/arq.pciconcursos.com.br\/sead-e-idema-rn-divulgam-concurso-publico-com-180-vagas\/1673652\/5373d4ff98\/edital_de_abertura_n_04_2025_1673652.pdf"
            }
        ]
    },
    {
        "regiao": "RIO GRANDE DO NORTE",
        "titulo": "IFRN - Instituto Federal de Educação, Ciência e Tecnologia",
        "link": "https:\/\/www.pciconcursos.com.br\/noticias\/ifrn-abre-concurso-publico-com-45-vagas-para-docentes",
        "imagem": "data:image\/png;base64,iVBORw0KGgoAAAANSUhEUgAAAAEAAAABCAYAAAAfFcSJAAAACXBIWXMAAA7EAAAOxAGVKw4bAAAADUlEQVQImWP4\/\/8\/AwAI\/AL+hc2rNAAAAABJRU5ErkJggg==",
        "resumo": "52 vagas até R$ 7107,99 Professor de Ensino Básico, Técnico e Tecnólogo Superior",
        "periodo_inscricao": "03\/06\/2025",
        "situacao": "Inscrição não iniciada",
        "link_apostila": [],
        "link_edital": [
            {
                "titulo": "EDITAL DE ABERTURA Nº 01\/2025",
                "url": "https:\/\/arq.pciconcursos.com.br\/ifrn-abre-concurso-publico-com-45-vagas-para-docentes\/1673139\/b1c8a81c86\/edital_de_abertura_n_01_2025_1673139.pdf"
            }
        ]
    },
    {
        "regiao": "SERGIPE",
        "titulo": "Cremese - Conselho Regional de Medicina do Estado de Sergipe",
        "link": "https:\/\/www.pciconcursos.com.br\/noticias\/cremese-abre-concurso-publico-para-cadastro-reserva-e-uma-vaga-em-aracaju-se",
        "imagem": "data:image\/png;base64,iVBORw0KGgoAAAANSUhEUgAAAAEAAAABCAYAAAAfFcSJAAAACXBIWXMAAA7EAAAOxAGVKw4bAAAADUlEQVQImWP4\/\/8\/AwAI\/AL+hc2rNAAAAABJRU5ErkJggg==",
        "resumo": "1 vaga até R$ 6275,81 Vários Cargos Médio \/ Superior",
        "periodo_inscricao": "20\/06\/2025",
        "situacao": "Inscrição não iniciada",
        "link_apostila": [],
        "link_edital": [
            {
                "titulo": "EDITAL DE ABERTURA Nº 01\/2025",
                "url": "https:\/\/arq.pciconcursos.com.br\/cremese-abre-concurso-publico-para-cadastro-reserva-e-uma-vaga-em-aracaju-se\/1673808\/263ed7c830\/edital_de_abertura_n_01_2025_1673808.pdf"
            }
        ]
    },
    {
        "regiao": "SERGIPE",
        "titulo": "Fundação Renascer",
        "link": "https:\/\/www.pciconcursos.com.br\/noticias\/fundacao-renascer-se-divulga-retificacao-de-concurso-publico",
        "imagem": "data:image\/png;base64,iVBORw0KGgoAAAANSUhEUgAAAAEAAAABCAYAAAAfFcSJAAAACXBIWXMAAA7EAAAOxAGVKw4bAAAADUlEQVQImWP4\/\/8\/AwAI\/AL+hc2rNAAAAABJRU5ErkJggg==",
        "resumo": "32 vagas até R$ 3308,76 Agente Socioeducativo Masculino, Agente Socioeducativo Feminino, Orientador Social Médio \/ Superior",
        "periodo_inscricao": "09\/06\/2025",
        "situacao": "Inscrição não iniciada",
        "link_apostila": [],
        "link_edital": [
            {
                "titulo": "EDITAL DE ABERTURA Nº 04\/2025 - RETIFICADO",
                "url": "https:\/\/arq.pciconcursos.com.br\/fundacao-renascer-se-divulga-retificacao-de-concurso-publico\/1673027\/8d332ac1f8\/edital_de_abertura_n_04_2025_retificado_1673027.pdf"
            },
            {
                "titulo": "EDITAL DE ABERTURA Nº 05\/2025",
                "url": "https:\/\/arq.pciconcursos.com.br\/fundacao-renascer-se-divulga-retificacao-de-concurso-publico\/1673028\/895556b7c3\/edital_de_abertura_n_05_2025_1673028.pdf"
            },
            {
                "titulo": "RETIFICAÇÃO I",
                "url": "https:\/\/arq.pciconcursos.com.br\/fundacao-renascer-se-divulga-retificacao-de-concurso-publico\/1674123\/44e0e592a3\/retificacao_i_1674123.pdf"
            }
        ]
    }
]